{
  "criteria": {
    "a": {
      "trigger": "player_hurt_entity",
      "conditions": {
        "damage": {
          "type": {
            "direct_entity": {
              "type": "player",
              "equipment": {
                "mainhand": {
                  "items": [
                    "minecraft:brush"
                  ],
                  "components": {
                    "minecraft:custom_name": {
                      "color": "white",
                      "italic": false,
                      "text": "朱雀羽扇"
                    }
                  }
                }
              }
            }
          }
        },
        "entity": {
          "type": "player"
        }
      }
    }
  },
  "rewards": {
    "function": "murder:job/6/1/trigger"
  }
}